classic/http_api/__init__.py
classic/http_api/app.py
classic/http_api/error_handlers.py
classic/http_api/utils.py
classic_http_api-0.0.2.dist-info/LICENSE
classic_http_api-0.0.2.dist-info/METADATA
classic_http_api-0.0.2.dist-info/WHEEL
classic_http_api-0.0.2.dist-info/top_level.txt
classic_http_api-0.0.2.dist-info/RECORD
